django_rest_swagger-2.1.2.dist-info/DESCRIPTION.rst
django_rest_swagger-2.1.2.dist-info/METADATA
django_rest_swagger-2.1.2.dist-info/RECORD
django_rest_swagger-2.1.2.dist-info/WHEEL
django_rest_swagger-2.1.2.dist-info/metadata.json
django_rest_swagger-2.1.2.dist-info/top_level.txt
rest_framework_swagger/__init__.py
rest_framework_swagger/renderers.py
rest_framework_swagger/settings.py
rest_framework_swagger/views.py
rest_framework_swagger/static/rest_framework_swagger/init.js
rest_framework_swagger/static/rest_framework_swagger/o2c.html
rest_framework_swagger/static/rest_framework_swagger/swagger-ui.js
rest_framework_swagger/static/rest_framework_swagger/swagger-ui.min.js
rest_framework_swagger/static/rest_framework_swagger/css/print.css
rest_framework_swagger/static/rest_framework_swagger/css/reset.css
rest_framework_swagger/static/rest_framework_swagger/css/screen.css
rest_framework_swagger/static/rest_framework_swagger/css/typography.css
rest_framework_swagger/static/rest_framework_swagger/fonts/DroidSans-Bold.ttf
rest_framework_swagger/static/rest_framework_swagger/fonts/DroidSans.ttf
rest_framework_swagger/static/rest_framework_swagger/images/collapse.gif
rest_framework_swagger/static/rest_framework_swagger/images/expand.gif
rest_framework_swagger/static/rest_framework_swagger/images/explorer_icons.png
rest_framework_swagger/static/rest_framework_swagger/images/favicon-16x16.png
rest_framework_swagger/static/rest_framework_swagger/images/favicon-32x32.png
rest_framework_swagger/static/rest_framework_swagger/images/favicon.ico
rest_framework_swagger/static/rest_framework_swagger/images/logo_small.png
rest_framework_swagger/static/rest_framework_swagger/images/pet_store_api.png
rest_framework_swagger/static/rest_framework_swagger/images/throbber.gif
rest_framework_swagger/static/rest_framework_swagger/images/wordnik_api.png
rest_framework_swagger/static/rest_framework_swagger/lang/en.js
rest_framework_swagger/static/rest_framework_swagger/lang/es.js
rest_framework_swagger/static/rest_framework_swagger/lang/fr.js
rest_framework_swagger/static/rest_framework_swagger/lang/geo.js
rest_framework_swagger/static/rest_framework_swagger/lang/it.js
rest_framework_swagger/static/rest_framework_swagger/lang/ja.js
